<package>
  <contactName>EAtech</contactName>
  <!-- Author name -->
  <contactEmail>EATechCMSupport@ea.com</contactEmail>
  <!-- Contact email address -->
  <summary>Example of how to build a library</summary>
  <!-- Please provide a summary of your library. -->
  <description>
    <p></p>
    <!-- Please describe your library. -->
  </description>
  <changes>
    <p></p>
    <!-- Please describe your changes. -->
  </changes>
  <homePageUrl></homePageUrl>
  <!-- Package Home Page, if any -->
  <frameworkVersion>2</frameworkVersion>
  <!-- Buildable Framework 2 package -->
  <buildable>true</buildable>
</package>