{
  "baseAttributes": {
    "platform": "PCWIN"
  }, 
  "countries": {
    "country": [
      {
        "attributes": {
          "isPurchasable": true
        }, 
        "countryCode": "AQ"
      }, 
      {
        "attributes": {
          "isPurchasable": true
        }, 
        "countryCode": "AS"
      }, 
      {
        "attributes": {
          "isPurchasable": true
        }, 
        "countryCode": "AU"
      }, 
      {
        "attributes": {
          "isPurchasable": false
        }, 
        "countryCode": "BD"
      }, 
      {
        "attributes": {
          "isPurchasable": false
        }, 
        "countryCode": "BT"
      }, 
      {
        "attributes": {
          "isPurchasable": true
        }, 
        "countryCode": "CK"
      }, 
      {
        "attributes": {
          "isPurchasable": true
        }, 
        "countryCode": "CX"
      }, 
      {
        "attributes": {
          "isPurchasable": true
        }, 
        "countryCode": "DEFAULT"
      }, 
      {
        "attributes": {
          "isPurchasable": true
        }, 
        "countryCode": "FJ"
      }, 
      {
        "attributes": {
          "isPurchasable": true
        }, 
        "countryCode": "FM"
      }, 
      {
        "attributes": {
          "isPurchasable": true
        }, 
        "countryCode": "GB"
      }, 
      {
        "attributes": {
          "isPurchasable": true
        }, 
        "countryCode": "GU"
      }, 
      {
        "attributes": {
          "isPurchasable": true
        }, 
        "countryCode": "HM"
      }, 
      {
        "attributes": {
          "isPurchasable": false
        }, 
        "countryCode": "IN"
      }, 
      {
        "attributes": {
          "isPurchasable": true
        }, 
        "countryCode": "KI"
      }, 
      {
        "attributes": {
          "isPurchasable": false
        }, 
        "countryCode": "LK"
      }, 
      {
        "attributes": {
          "isPurchasable": true
        }, 
        "countryCode": "MH"
      }, 
      {
        "attributes": {
          "isPurchasable": true
        }, 
        "countryCode": "NF"
      }, 
      {
        "attributes": {
          "isPurchasable": false
        }, 
        "countryCode": "NP"
      }, 
      {
        "attributes": {
          "isPurchasable": true
        }, 
        "countryCode": "NR"
      }, 
      {
        "attributes": {
          "isPurchasable": true
        }, 
        "countryCode": "NU"
      }, 
      {
        "attributes": {
          "isPurchasable": true
        }, 
        "countryCode": "PG"
      }, 
      {
        "attributes": {
          "isPurchasable": false
        }, 
        "countryCode": "PK"
      }, 
      {
        "attributes": {
          "isPurchasable": true
        }, 
        "countryCode": "PR"
      }, 
      {
        "attributes": {
          "isPurchasable": true
        }, 
        "countryCode": "PW"
      }, 
      {
        "attributes": {
          "isPurchasable": true
        }, 
        "countryCode": "SB"
      }, 
      {
        "attributes": {
          "isPurchasable": true
        }, 
        "countryCode": "TK"
      }, 
      {
        "attributes": {
          "isPurchasable": true
        }, 
        "countryCode": "TV"
      }, 
      {
        "attributes": {
          "isPurchasable": true
        }, 
        "countryCode": "US"
      }, 
      {
        "attributes": {
          "isPurchasable": true
        }, 
        "countryCode": "VI"
      }, 
      {
        "attributes": {
          "isPurchasable": true
        }, 
        "countryCode": "VU"
      }
    ]
  }, 
  "customAttributes": {
    "imageServer": "https://Eaassets-a.akamaihd.net/origin-com-store-final-assets-prod"
  }, 
  "defaultLocale": "DEFAULT", 
  "ecommerceAttributes": {
    "addonsAvailable": false, 
    "availableExtraContent": [], 
    "cdnAssetRoot": "http://static.cdn.ea.com/ebisu/u/f/products/1005299"
  }, 
  "financeId": "1005299", 
  "itemId": "Origin.ITM.50.0000709", 
  "localizableAttributes": {
    "displayName": "Dragon Age™: Inquisition - Hakkons Fänge", 
    "longDescription": "Du hast die Inquisition erfolgreich in den Kampf gegen die Dämonen-Truppen des Nichts geführt – jetzt ist es an der Zeit, mit deinen Anhängern zu einer neuen gefährlichen Einzelspielermission aufzubrechen, die ein vergessenes Kapitel in der Geschichte der Inquisition beleuchtet. Wage dich in ein vollkommen neues Gebiet mit üppigen Wäldern, Bergregionen und mächtigen neuen Feinden. Lerne die Avvar kennen: unabhängige Jäger, deren reiche Tradition dir dabei hilft, Licht in das Schicksal des letzten Inquisitors zu bringen. Erkunde eine alte Tevinter-Festung, die ein gefährliches Geheimnis birgt. Eigne dir auf deinen Reisen legendäre Waffen und Rüstungen an und konfrontiere einen uralten Kriegsgott, der entschlossen ist, die Welt zu zerstören. Deine Reise ist noch nicht zu Ende, Inquisitor.<br><br>\n<b>Erkunde ein völlig neues Gebiet.</b> Begib dich auf neue Missionen, bekämpfe neue Feinde und verdiene dir den Respekt der Avvar, eines Jägerstammes, der in den südlichen Bergregionen von Thedas lebt. <br><br>\n<b>Beleuchte ein vergessenes Kapitel in der Geschichte der Inquisition.</b> Stürze dich in ein neues Abenteuer, um das Schicksal des letzten Inquisitors und des von ihm verfolgten Drachen zu ergründen. <br><br>\n<b>Stärke die Inquisition weiter.</b> Steigere deine Macht mit legendären Waffen und Rüstungen und widme dich neuen Operationen am Kartentisch.", 
    "packArtLarge": "/74369/231.0x326.0/1005299_LB_231x326_en_US_^_2015-03-02-13-15-28_aef18c157437f47565f05c9601ca0416413aba87.jpg", 
    "packArtMedium": "/74369/142.0x200.0/1005299_MB_142x200_en_US_^_2015-03-02-12-57-17_6014c5da40b40c55031a3a086134001755a1f2cf.jpg", 
    "packArtSmall": "/74369/63.0x89.0/1005299_SB_63x89_en_US_^_2015-03-02-12-58-46_43b34dc08f270db47505df570801ec508cdff0ca.jpg", 
    "shortDescription": "Das epische Abenteuer geht weiter."
  }, 
  "mdmHierarchies": {
    "mdmHierarchy": [
      {
        "mdmFranchise": {
          "franchise": "Dragon Age", 
          "franchiseId": 68222
        }, 
        "mdmMasterTitle": {
          "masterTitle": "DRAGON AGE: INQUISITION", 
          "masterTitleId": 74369
        }, 
        "type": "Primary"
      }
    ]
  }, 
  "offerId": "Origin.OFR.50.0000675", 
  "offerType": "Extra Content", 
  "publishing": {
    "publishingAttributes": {
      "contentId": "1005299", 
      "isDownloadable": true, 
      "isPublished": true, 
      "originDisplayType": "Addon"
    }, 
    "softwareControlDates": {
      "softwareControlDate": [
        {
          "downloadStartDate": "2024-08-22T23:23:12Z", 
          "platform": "PCWIN"
        }
      ]
    }, 
    "softwareList": {
      "software": [
        {
          "downloadURLs": {
            "downloadURL": [
              {
                "buildMetaData": "<?xml version=\"1.0\" encoding=\"UTF-8\"?><buildMetaData>    <gameVersion version=\"1.0.0.0\"/>    <featureFlags dynamicContentSupportEnabled=\"0\" enableDifferentialUpdate=\"1\"/>  </buildMetaData>", 
                "buildReleaseVersion": "1.0.0.0", 
                "downloadURL": "/shift/da_i/da_i_pc_dlc__ww_sp_dlc1_production_46__build876513dlc_3193bf3eeba54829b079692b785a6ce5.zip", 
                "downloadURLType": "live", 
                "effectiveDate": "2015-03-17T12:27:56Z"
              }
            ]
          }, 
          "fulfillmentAttributes": {
            "downloadPackageType": "DownloadInPlace", 
            "installCheckOverride": "[HKEY_LOCAL_MACHINE\\SOFTWARE\\BioWare\\Dragon Age Inquisition\\Install Dir]\\Update\\Singleplayer_DLC1\\package.mft", 
            "installationDirectory": "\\", 
            "metadataInstallLocation": "\\__Installer\\DLC\\Singleplayer_DLC1", 
            "monitorInstall": true, 
            "monitorPlay": true, 
            "showKeyDialogOnInstall": false, 
            "showKeyDialogOnPlay": false
          }, 
          "softwarePlatform": "PCWIN"
        }
      ]
    }, 
    "softwareLocales": {
      "locale": [
        {
          "value": "de_DE"
        }, 
        {
          "value": "en_GB"
        }, 
        {
          "value": "en_US"
        }, 
        {
          "value": "es_ES"
        }, 
        {
          "value": "fr_FR"
        }, 
        {
          "value": "it_IT"
        }, 
        {
          "value": "ja_JP"
        }, 
        {
          "value": "pl_PL"
        }, 
        {
          "value": "pt_BR"
        }, 
        {
          "value": "ru_RU"
        }
      ]
    }
  }, 
  "updatedDate": "2015-03-13T06:13:01Z"
}